cpu/define.v
`define RstEnable 1'b1
`define RstDisable 1'b0
`define ZeroWord 32'h00000000
`define WriteEnable 1'b1
`define WriteDisable 1'b0
`define ReadEnable 1'b1
`define ReadDisable 1'b0
`define AluOpBus 7:0
`define AluSelBus 2:0
`define InstValid 1'b1
`define InstInvalid 1'b0
`define True_v 1'b1
`define False_v 1'b0
`define ChipEnable 1'b1
`define ChipDisable 1'b0

`define EXE_ORI 6'b001101
`define EXE_NOP 6'b000000

`define EXE_OR_OP 8'b00100101
`define EXE_NOP_OP 8'b00000000

`define EXE_RES_LOGIC 3'b001
`define EXE_RES_NOP 3'b000

`define InstAddrBus 31:0
`define InstBus 31:0
`define InstMemNum 131071 // 128KB
`define InstMemNumLog2 17

`define RegAddrBus 4:0
`define RegBus 31:0
`define RegWidth 32
`define DoubleRegWidth 64
`define DoubleRegBus 63:0
`define RegNum 32
`define RegNumLog2 5
`define NOPRegAddr 5'b0000

cpu/id.v
`include "define.v"
module id(
    input wire rst,
    input wire[`InstAddrBus] pc_i,
    input wire[`InstBus] inst_i,

    input wire[`RegBus] reg1_data_i, // read reg1 data
    input wire[`RegBus] reg2_data_i, // read reg2 data

    output reg reg1_read_o, // read reg1 or not
    output reg reg2_read_o, // read reg2 or not
    output reg[`RegAddrBus] reg1_addr_o, // read reg1 num
    output reg[`RegAddrBus] reg2_addr_o, // read reg2 num

    output reg[`AluOpBus] aluop_o, // alu op
    output reg[`AluSelBus] alusel_o, // alu selector
    output reg[`RegBus] reg1_o, // reg1 passed to alu
    output reg[`RegBus] reg2_o, // reg2 passed to alu
    output reg[`RegAddrBus] wd_o, // output register num
    output reg wreg_o // output enabled
);
    wire[5:0] op = inst_i[31:26]; // op type
    wire[4:0] op2 = inst_i[10:6];
    wire[5:0] op3 = inst_i[5:0];
    wire[4:0] op4 = inst_i[20:16];

    reg[`RegBus] imm;
    reg instvalid;

    always @ (*) begin
      if (rst == `RstEnable) begin
        aluop_o <= `EXE_NOP_OP;
        alusel_o <= `EXE_RES_NOP;
        wd_o <= `NOPRegAddr;
        wreg_o <= `WriteDisable;
        instvalid <= `InstValid;
        reg1_read_o <= 1'0;
        reg2_read_o <= 1'0;
        reg1_addr_o <= `NOPRegAddr;
        reg2_addr_o <= `NOPRegAddr;
        imm <= `ZeroWord;
      end else begin
        aluop_o <= `EXE_NOP_OP;
        alusel_o <= `EXE_RES_NOP;
        wd_o <= inst_i[15:11];
        wreg_o <= `WriteDisable;
        instvalid <= `InstInvalid;
        reg1_read_o <= 1'0;
        reg2_read_o <= 1'0;
        reg1_addr_o <= inst_i[25:21];
        reg2_addr_o <= inst_i[20:16];
        imm <= `ZeroWord;

        case (op)
          `EXE_ORI: begin
            wreg_o <= `WriteEnable;
            aluop_o <= `EXE_OR_OP;
            alusel_o <= `EXE_RES_LOGIC;
            reg1_read_o <= 1'1; // read source from rs
            reg2_read_o <= 1'0; // use imm
            // unsigned extend
            imm <= {16'h0, inst_i[15:0]};
            wd_o <= inst_i[20:16];
            instvalid <= `InstValid;
          end
          default: begin
            
          end
        endcase
      end
    end

    always @ (*) begin
      if (rst == `RstEnable) begin
        reg1_o <= `ZeroWord;
      end else if (reg1_read_o == 1'b1) begin
        reg1_o <= reg1_data_i;
      end else if (reg1_read_o == 1'b0) begin
        reg1_o <= imm;
      end else begin
        reg1_o <= `ZeroWord;
      end
    end

    always @ (*) begin
      if (rst == `RstEnable) begin
        reg2_o <= `ZeroWord;
      end else if (reg2_read_o == 1'b1) begin
        reg2_o <= reg2_data_i;
      end else if (reg2_read_o == 1'b0) begin
        reg2_o <= imm;
      end else begin
        reg2_o <= `ZeroWord;
      end
    end

endmodule // id

cpu/id.vcd
$version Generated by VerilatedVcd $end
$date Thu Jun 21 21:11:16 2018
 $end
$timescale   1ns $end

 $scope module TOP $end
  $var wire  8 . aluop_o [7:0] $end
  $var wire  3 / alusel_o [2:0] $end
  $var wire 32 ' inst_i [31:0] $end
  $var wire 32 & pc_i [31:0] $end
  $var wire  5 , reg1_addr_o [4:0] $end
  $var wire 32 ( reg1_data_i [31:0] $end
  $var wire 32 0 reg1_o [31:0] $end
  $var wire  1 * reg1_read_o $end
  $var wire  5 - reg2_addr_o [4:0] $end
  $var wire 32 ) reg2_data_i [31:0] $end
  $var wire 32 1 reg2_o [31:0] $end
  $var wire  1 + reg2_read_o $end
  $var wire  1 % rst $end
  $var wire  5 2 wd_o [4:0] $end
  $var wire  1 3 wreg_o $end
  $scope module id $end
   $var wire  8 . aluop_o [7:0] $end
   $var wire  3 / alusel_o [2:0] $end
   $var wire 32 # imm [31:0] $end
   $var wire 32 ' inst_i [31:0] $end
   $var wire  1 $ instvalid $end
   $var wire  6 4 op [5:0] $end
   $var wire  5 5 op2 [4:0] $end
   $var wire  6 6 op3 [5:0] $end
   $var wire  5 7 op4 [4:0] $end
   $var wire 32 & pc_i [31:0] $end
   $var wire  5 , reg1_addr_o [4:0] $end
   $var wire 32 ( reg1_data_i [31:0] $end
   $var wire 32 0 reg1_o [31:0] $end
   $var wire  1 * reg1_read_o $end
   $var wire  5 - reg2_addr_o [4:0] $end
   $var wire 32 ) reg2_data_i [31:0] $end
   $var wire 32 1 reg2_o [31:0] $end
   $var wire  1 + reg2_read_o $end
   $var wire  1 % rst $end
   $var wire  5 2 wd_o [4:0] $end
   $var wire  1 3 wreg_o $end
  $upscope $end
 $upscope $end
$enddefinitions $end


#0
b00000000000000000101010101010101 #
0$
0%
b00010010001101000101011001111000 &
b00110100001010100101010101010101 '
b00000000000000000000000000000000 (
b00000000000000000000000000000000 )
1*
0+
b00001 ,
b01010 -
b00100101 .
b001 /
b00000000000000000000000000000000 0
b00000000000000000101010101010101 1
b01010 2
13
b001101 4
b10101 5
b010101 6
b01010 7
#1
b00000000000000000000000000000000 #
1%
0*
b00000 ,
b00000 -
b00000000 .
b000 /
b00000000000000000000000000000000 1
b00000 2
03
#2
b00000000000000000101010101010101 #
0%
b00000000000000000000000000000001 (
1*
b00001 ,
b01010 -
b00100101 .
b001 /
b00000000000000000000000000000001 0
b00000000000000000101010101010101 1
b01010 2
13
#3
b00000000000000000000000000000000 #
1%
0*
b00000 ,
b00000 -
b00000000 .
b000 /
b00000000000000000000000000000000 0
b00000000000000000000000000000000 1
b00000 2
03
#4
b00000000000000000101010101010101 #
0%
b00000000000000000000000000000010 (
1*
b00001 ,
b01010 -
b00100101 .
b001 /
b00000000000000000000000000000010 0
b00000000000000000101010101010101 1
b01010 2
13
#5
b00000000000000000000000000000000 #
1%
0*
b00000 ,
b00000 -
b00000000 .
b000 /
b00000000000000000000000000000000 0
b00000000000000000000000000000000 1
b00000 2
03
#6
b00000000000000000101010101010101 #
0%
b00000000000000000000000000000011 (
1*
b00001 ,
b01010 -
b00100101 .
b001 /
b00000000000000000000000000000011 0
b00000000000000000101010101010101 1
b01010 2
13
#7
b00000000000000000000000000000000 #
1%
0*
b00000 ,
b00000 -
b00000000 .
b000 /
b00000000000000000000000000000000 0
b00000000000000000000000000000000 1
b00000 2
03
#8
b00000000000000000101010101010101 #
0%
b00000000000000000000000000000100 (
1*
b00001 ,
b01010 -
b00100101 .
b001 /
b00000000000000000000000000000100 0
b00000000000000000101010101010101 1
b01010 2
13
#9
b00000000000000000000000000000000 #
1%
0*
b00000 ,
b00000 -
b00000000 .
b000 /
b00000000000000000000000000000000 0
b00000000000000000000000000000000 1
b00000 2
03
#10
b00000000000000000101010101010101 #
0%
b00000000000000000000000000000101 (
1*
b00001 ,
b01010 -
b00100101 .
b001 /
b00000000000000000000000000000101 0
b00000000000000000101010101010101 1
b01010 2
13
#11
b00000000000000000000000000000000 #
1%
0*
b00000 ,
b00000 -
b00000000 .
b000 /
b00000000000000000000000000000000 0
b00000000000000000000000000000000 1
b00000 2
03
#12
b00000000000000000101010101010101 #
0%
b00000000000000000000000000000110 (
1*
b00001 ,
b01010 -
b00100101 .
b001 /
b00000000000000000000000000000110 0
b00000000000000000101010101010101 1
b01010 2
13
#13
b00000000000000000000000000000000 #
1%
0*
b00000 ,
b00000 -
b00000000 .
b000 /
b00000000000000000000000000000000 0
b00000000000000000000000000000000 1
b00000 2
03
#14
b00000000000000000101010101010101 #
0%
b00000000000000000000000000000111 (
1*
b00001 ,
b01010 -
b00100101 .
b001 /
b00000000000000000000000000000111 0
b00000000000000000101010101010101 1
b01010 2
13
#15
b00000000000000000000000000000000 #
1%
0*
b00000 ,
b00000 -
b00000000 .
b000 /
b00000000000000000000000000000000 0
b00000000000000000000000000000000 1
b00000 2
03
#16
b00000000000000000101010101010101 #
0%
b00000000000000000000000000001000 (
1*
b00001 ,
b01010 -
b00100101 .
b001 /
b00000000000000000000000000001000 0
b00000000000000000101010101010101 1
b01010 2
13
#17
b00000000000000000000000000000000 #
1%
0*
b00000 ,
b00000 -
b00000000 .
b000 /
b00000000000000000000000000000000 0
b00000000000000000000000000000000 1
b00000 2
03
#18
b00000000000000000101010101010101 #
0%
b00000000000000000000000000001001 (
1*
b00001 ,
b01010 -
b00100101 .
b001 /
b00000000000000000000000000001001 0
b00000000000000000101010101010101 1
b01010 2
13
#19
b00000000000000000000000000000000 #
1%
0*
b00000 ,
b00000 -
b00000000 .
b000 /
b00000000000000000000000000000000 0
b00000000000000000000000000000000 1
b00000 2
03
#20
b00000000000000000101010101010101 #
0%
b00000000000000000000000000001010 (
1*
b00001 ,
b01010 -
b00100101 .
b001 /
b00000000000000000000000000001010 0
b00000000000000000101010101010101 1
b01010 2
13
#21
b00000000000000000000000000000000 #
1%
0*
b00000 ,
b00000 -
b00000000 .
b000 /
b00000000000000000000000000000000 0
b00000000000000000000000000000000 1
b00000 2
03
#22
b00000000000000000101010101010101 #
0%
b00000000000000000000000000001011 (
1*
b00001 ,
b01010 -
b00100101 .
b001 /
b00000000000000000000000000001011 0
b00000000000000000101010101010101 1
b01010 2
13
#23
b00000000000000000000000000000000 #
1%
0*
b00000 ,
b00000 -
b00000000 .
b000 /
b00000000000000000000000000000000 0
b00000000000000000000000000000000 1
b00000 2
03
#24
b00000000000000000101010101010101 #
0%
b00000000000000000000000000001100 (
1*
b00001 ,
b01010 -
b00100101 .
b001 /
b00000000000000000000000000001100 0
b00000000000000000101010101010101 1
b01010 2
13
#25
b00000000000000000000000000000000 #
1%
0*
b00000 ,
b00000 -
b00000000 .
b000 /
b00000000000000000000000000000000 0
b00000000000000000000000000000000 1
b00000 2
03
#26
b00000000000000000101010101010101 #
0%
b00000000000000000000000000001101 (
1*
b00001 ,
b01010 -
b00100101 .
b001 /
b00000000000000000000000000001101 0
b00000000000000000101010101010101 1
b01010 2
13
#27
b00000000000000000000000000000000 #
1%
0*
b00000 ,
b00000 -
b00000000 .
b000 /
b00000000000000000000000000000000 0
b00000000000000000000000000000000 1
b00000 2
03
#28
b00000000000000000101010101010101 #
0%
b00000000000000000000000000001110 (
1*
b00001 ,
b01010 -
b00100101 .
b001 /
b00000000000000000000000000001110 0
b00000000000000000101010101010101 1
b01010 2
13
#29
b00000000000000000000000000000000 #
1%
0*
b00000 ,
b00000 -
b00000000 .
b000 /
b00000000000000000000000000000000 0
b00000000000000000000000000000000 1
b00000 2
03
#30
b00000000000000000101010101010101 #
0%
b00000000000000000000000000001111 (
1*
b00001 ,
b01010 -
b00100101 .
b001 /
b00000000000000000000000000001111 0
b00000000000000000101010101010101 1
b01010 2
13
#31
b00000000000000000000000000000000 #
1%
0*
b00000 ,
b00000 -
b00000000 .
b000 /
b00000000000000000000000000000000 0
b00000000000000000000000000000000 1
b00000 2
03
#32
b00000000000000000101010101010101 #
0%
b00000000000000000000000000010000 (
1*
b00001 ,
b01010 -
b00100101 .
b001 /
b00000000000000000000000000010000 0
b00000000000000000101010101010101 1
b01010 2
13
#33
b00000000000000000000000000000000 #
1%
0*
b00000 ,
b00000 -
b00000000 .
b000 /
b00000000000000000000000000000000 0
b00000000000000000000000000000000 1
b00000 2
03
#34
b00000000000000000101010101010101 #
0%
b00000000000000000000000000010001 (
1*
b00001 ,
b01010 -
b00100101 .
b001 /
b00000000000000000000000000010001 0
b00000000000000000101010101010101 1
b01010 2
13
#35
b00000000000000000000000000000000 #
1%
0*
b00000 ,
b00000 -
b00000000 .
b000 /
b00000000000000000000000000000000 0
b00000000000000000000000000000000 1
b00000 2
03
#36
b00000000000000000101010101010101 #
0%
b00000000000000000000000000010010 (
1*
b00001 ,
b01010 -
b00100101 .
b001 /
b00000000000000000000000000010010 0
b00000000000000000101010101010101 1
b01010 2
13
#37
b00000000000000000000000000000000 #
1%
0*
b00000 ,
b00000 -
b00000000 .
b000 /
b00000000000000000000000000000000 0
b00000000000000000000000000000000 1
b00000 2
03
#38
b00000000000000000101010101010101 #
0%
b00000000000000000000000000010011 (
1*
b00001 ,
b01010 -
b00100101 .
b001 /
b00000000000000000000000000010011 0
b00000000000000000101010101010101 1
b01010 2
13
#39
b00000000000000000000000000000000 #
1%
0*
b00000 ,
b00000 -
b00000000 .
b000 /
b00000000000000000000000000000000 0
b00000000000000000000000000000000 1
b00000 2
03
#40
b00000000000000000101010101010101 #
0%
b00000000000000000000000000010100 (
1*
b00001 ,
b01010 -
b00100101 .
b001 /
b00000000000000000000000000010100 0
b00000000000000000101010101010101 1
b01010 2
13
#41
b00000000000000000000000000000000 #
1%
0*
b00000 ,
b00000 -
b00000000 .
b000 /
b00000000000000000000000000000000 0
b00000000000000000000000000000000 1
b00000 2
03
#42
b00000000000000000101010101010101 #
0%
b00000000000000000000000000010101 (
1*
b00001 ,
b01010 -
b00100101 .
b001 /
b00000000000000000000000000010101 0
b00000000000000000101010101010101 1
b01010 2
13
#43
b00000000000000000000000000000000 #
1%
0*
b00000 ,
b00000 -
b00000000 .
b000 /
b00000000000000000000000000000000 0
b00000000000000000000000000000000 1
b00000 2
03
#44
b00000000000000000101010101010101 #
0%
b00000000000000000000000000010110 (
1*
b00001 ,
b01010 -
b00100101 .
b001 /
b00000000000000000000000000010110 0
b00000000000000000101010101010101 1
b01010 2
13
#45
b00000000000000000000000000000000 #
1%
0*
b00000 ,
b00000 -
b00000000 .
b000 /
b00000000000000000000000000000000 0
b00000000000000000000000000000000 1
b00000 2
03
#46
b00000000000000000101010101010101 #
0%
b00000000000000000000000000010111 (
1*
b00001 ,
b01010 -
b00100101 .
b001 /
b00000000000000000000000000010111 0
b00000000000000000101010101010101 1
b01010 2
13
#47
b00000000000000000000000000000000 #
1%
0*
b00000 ,
b00000 -
b00000000 .
b000 /
b00000000000000000000000000000000 0
b00000000000000000000000000000000 1
b00000 2
03
#48
b00000000000000000101010101010101 #
0%
b00000000000000000000000000011000 (
1*
b00001 ,
b01010 -
b00100101 .
b001 /
b00000000000000000000000000011000 0
b00000000000000000101010101010101 1
b01010 2
13
#49
b00000000000000000000000000000000 #
1%
0*
b00000 ,
b00000 -
b00000000 .
b000 /
b00000000000000000000000000000000 0
b00000000000000000000000000000000 1
b00000 2
03
#50
b00000000000000000101010101010101 #
0%
b00000000000000000000000000011001 (
1*
b00001 ,
b01010 -
b00100101 .
b001 /
b00000000000000000000000000011001 0
b00000000000000000101010101010101 1
b01010 2
13
#51
b00000000000000000000000000000000 #
1%
0*
b00000 ,
b00000 -
b00000000 .
b000 /
b00000000000000000000000000000000 0
b00000000000000000000000000000000 1
b00000 2
03
#52
b00000000000000000101010101010101 #
0%
b00000000000000000000000000011010 (
1*
b00001 ,
b01010 -
b00100101 .
b001 /
b00000000000000000000000000011010 0
b00000000000000000101010101010101 1
b01010 2
13
#53
b00000000000000000000000000000000 #
1%
0*
b00000 ,
b00000 -
b00000000 .
b000 /
b00000000000000000000000000000000 0
b00000000000000000000000000000000 1
b00000 2
03
#54
b00000000000000000101010101010101 #
0%
b00000000000000000000000000011011 (
1*
b00001 ,
b01010 -
b00100101 .
b001 /
b00000000000000000000000000011011 0
b00000000000000000101010101010101 1
b01010 2
13
#55
b00000000000000000000000000000000 #
1%
0*
b00000 ,
b00000 -
b00000000 .
b000 /
b00000000000000000000000000000000 0
b00000000000000000000000000000000 1
b00000 2
03
#56
b00000000000000000101010101010101 #
0%
b00000000000000000000000000011100 (
1*
b00001 ,
b01010 -
b00100101 .
b001 /
b00000000000000000000000000011100 0
b00000000000000000101010101010101 1
b01010 2
13
#57
b00000000000000000000000000000000 #
1%
0*
b00000 ,
b00000 -
b00000000 .
b000 /
b00000000000000000000000000000000 0
b00000000000000000000000000000000 1
b00000 2
03
#58
b00000000000000000101010101010101 #
0%
b00000000000000000000000000011101 (
1*
b00001 ,
b01010 -
b00100101 .
b001 /
b00000000000000000000000000011101 0
b00000000000000000101010101010101 1
b01010 2
13
#59
b00000000000000000000000000000000 #
1%
0*
b00000 ,
b00000 -
b00000000 .
b000 /
b00000000000000000000000000000000 0
b00000000000000000000000000000000 1
b00000 2
03
#60
b00000000000000000101010101010101 #
0%
b00000000000000000000000000011110 (
1*
b00001 ,
b01010 -
b00100101 .
b001 /
b00000000000000000000000000011110 0
b00000000000000000101010101010101 1
b01010 2
13
#61
b00000000000000000000000000000000 #
1%
0*
b00000 ,
b00000 -
b00000000 .
b000 /
b00000000000000000000000000000000 0
b00000000000000000000000000000000 1
b00000 2
03
#62
b00000000000000000101010101010101 #
0%
b00000000000000000000000000011111 (
1*
b00001 ,
b01010 -
b00100101 .
b001 /
b00000000000000000000000000011111 0
b00000000000000000101010101010101 1
b01010 2
13
#63
b00000000000000000000000000000000 #
1%
0*
b00000 ,
b00000 -
b00000000 .
b000 /
b00000000000000000000000000000000 0
b00000000000000000000000000000000 1
b00000 2
03
#64
b00000000000000000101010101010101 #
0%
b00000000000000000000000000100000 (
1*
b00001 ,
b01010 -
b00100101 .
b001 /
b00000000000000000000000000100000 0
b00000000000000000101010101010101 1
b01010 2
13
#65
b00000000000000000000000000000000 #
1%
0*
b00000 ,
b00000 -
b00000000 .
b000 /
b00000000000000000000000000000000 0
b00000000000000000000000000000000 1
b00000 2
03
#66
b00000000000000000101010101010101 #
0%
b00000000000000000000000000100001 (
1*
b00001 ,
b01010 -
b00100101 .
b001 /
b00000000000000000000000000100001 0
b00000000000000000101010101010101 1
b01010 2
13
#67
b00000000000000000000000000000000 #
1%
0*
b00000 ,
b00000 -
b00000000 .
b000 /
b00000000000000000000000000000000 0
b00000000000000000000000000000000 1
b00000 2
03
#68
b00000000000000000101010101010101 #
0%
b00000000000000000000000000100010 (
1*
b00001 ,
b01010 -
b00100101 .
b001 /
b00000000000000000000000000100010 0
b00000000000000000101010101010101 1
b01010 2
13
#69
b00000000000000000000000000000000 #
1%
0*
b00000 ,
b00000 -
b00000000 .
b000 /
b00000000000000000000000000000000 0
b00000000000000000000000000000000 1
b00000 2
03
#70
b00000000000000000101010101010101 #
0%
b00000000000000000000000000100011 (
1*
b00001 ,
b01010 -
b00100101 .
b001 /
b00000000000000000000000000100011 0
b00000000000000000101010101010101 1
b01010 2
13
#71
b00000000000000000000000000000000 #
1%
0*
b00000 ,
b00000 -
b00000000 .
b000 /
b00000000000000000000000000000000 0
b00000000000000000000000000000000 1
b00000 2
03
#72
b00000000000000000101010101010101 #
0%
b00000000000000000000000000100100 (
1*
b00001 ,
b01010 -
b00100101 .
b001 /
b00000000000000000000000000100100 0
b00000000000000000101010101010101 1
b01010 2
13
#73
b00000000000000000000000000000000 #
1%
0*
b00000 ,
b00000 -
b00000000 .
b000 /
b00000000000000000000000000000000 0
b00000000000000000000000000000000 1
b00000 2
03
#74
b00000000000000000101010101010101 #
0%
b00000000000000000000000000100101 (
1*
b00001 ,
b01010 -
b00100101 .
b001 /
b00000000000000000000000000100101 0
b00000000000000000101010101010101 1
b01010 2
13
#75
b00000000000000000000000000000000 #
1%
0*
b00000 ,
b00000 -
b00000000 .
b000 /
b00000000000000000000000000000000 0
b00000000000000000000000000000000 1
b00000 2
03
#76
b00000000000000000101010101010101 #
0%
b00000000000000000000000000100110 (
1*
b00001 ,
b01010 -
b00100101 .
b001 /
b00000000000000000000000000100110 0
b00000000000000000101010101010101 1
b01010 2
13
#77
b00000000000000000000000000000000 #
1%
0*
b00000 ,
b00000 -
b00000000 .
b000 /
b00000000000000000000000000000000 0
b00000000000000000000000000000000 1
b00000 2
03
#78
b00000000000000000101010101010101 #
0%
b00000000000000000000000000100111 (
1*
b00001 ,
b01010 -
b00100101 .
b001 /
b00000000000000000000000000100111 0
b00000000000000000101010101010101 1
b01010 2
13
#79
b00000000000000000000000000000000 #
1%
0*
b00000 ,
b00000 -
b00000000 .
b000 /
b00000000000000000000000000000000 0
b00000000000000000000000000000000 1
b00000 2
03
#80
b00000000000000000101010101010101 #
0%
b00000000000000000000000000101000 (
1*
b00001 ,
b01010 -
b00100101 .
b001 /
b00000000000000000000000000101000 0
b00000000000000000101010101010101 1
b01010 2
13
#81
b00000000000000000000000000000000 #
1%
0*
b00000 ,
b00000 -
b00000000 .
b000 /
b00000000000000000000000000000000 0
b00000000000000000000000000000000 1
b00000 2
03
#82
b00000000000000000101010101010101 #
0%
b00000000000000000000000000101001 (
1*
b00001 ,
b01010 -
b00100101 .
b001 /
b00000000000000000000000000101001 0
b00000000000000000101010101010101 1
b01010 2
13
#83
b00000000000000000000000000000000 #
1%
0*
b00000 ,
b00000 -
b00000000 .
b000 /
b00000000000000000000000000000000 0
b00000000000000000000000000000000 1
b00000 2
03
#84
b00000000000000000101010101010101 #
0%
b00000000000000000000000000101010 (
1*
b00001 ,
b01010 -
b00100101 .
b001 /
b00000000000000000000000000101010 0
b00000000000000000101010101010101 1
b01010 2
13
#85
b00000000000000000000000000000000 #
1%
0*
b00000 ,
b00000 -
b00000000 .
b000 /
b00000000000000000000000000000000 0
b00000000000000000000000000000000 1
b00000 2
03
#86
b00000000000000000101010101010101 #
0%
b00000000000000000000000000101011 (
1*
b00001 ,
b01010 -
b00100101 .
b001 /
b00000000000000000000000000101011 0
b00000000000000000101010101010101 1
b01010 2
13
#87
b00000000000000000000000000000000 #
1%
0*
b00000 ,
b00000 -
b00000000 .
b000 /
b00000000000000000000000000000000 0
b00000000000000000000000000000000 1
b00000 2
03
#88
b00000000000000000101010101010101 #
0%
b00000000000000000000000000101100 (
1*
b00001 ,
b01010 -
b00100101 .
b001 /
b00000000000000000000000000101100 0
b00000000000000000101010101010101 1
b01010 2
13
#89
b00000000000000000000000000000000 #
1%
0*
b00000 ,
b00000 -
b00000000 .
b000 /
b00000000000000000000000000000000 0
b00000000000000000000000000000000 1
b00000 2
03
#90
b00000000000000000101010101010101 #
0%
b00000000000000000000000000101101 (
1*
b00001 ,
b01010 -
b00100101 .
b001 /
b00000000000000000000000000101101 0
b00000000000000000101010101010101 1
b01010 2
13
#91
b00000000000000000000000000000000 #
1%
0*
b00000 ,
b00000 -
b00000000 .
b000 /
b00000000000000000000000000000000 0
b00000000000000000000000000000000 1
b00000 2
03
#92
b00000000000000000101010101010101 #
0%
b00000000000000000000000000101110 (
1*
b00001 ,
b01010 -
b00100101 .
b001 /
b00000000000000000000000000101110 0
b00000000000000000101010101010101 1
b01010 2
13
#93
b00000000000000000000000000000000 #
1%
0*
b00000 ,
b00000 -
b00000000 .
b000 /
b00000000000000000000000000000000 0
b00000000000000000000000000000000 1
b00000 2
03
#94
b00000000000000000101010101010101 #
0%
b00000000000000000000000000101111 (
1*
b00001 ,
b01010 -
b00100101 .
b001 /
b00000000000000000000000000101111 0
b00000000000000000101010101010101 1
b01010 2
13
#95
b00000000000000000000000000000000 #
1%
0*
b00000 ,
b00000 -
b00000000 .
b000 /
b00000000000000000000000000000000 0
b00000000000000000000000000000000 1
b00000 2
03
#96
b00000000000000000101010101010101 #
0%
b00000000000000000000000000110000 (
1*
b00001 ,
b01010 -
b00100101 .
b001 /
b00000000000000000000000000110000 0
b00000000000000000101010101010101 1
b01010 2
13
#97
b00000000000000000000000000000000 #
1%
0*
b00000 ,
b00000 -
b00000000 .
b000 /
b00000000000000000000000000000000 0
b00000000000000000000000000000000 1
b00000 2
03
#98
b00000000000000000101010101010101 #
0%
b00000000000000000000000000110001 (
1*
b00001 ,
b01010 -
b00100101 .
b001 /
b00000000000000000000000000110001 0
b00000000000000000101010101010101 1
b01010 2
13
#99
b00000000000000000000000000000000 #
1%
0*
b00000 ,
b00000 -
b00000000 .
b000 /
b00000000000000000000000000000000 0
b00000000000000000000000000000000 1
b00000 2
03
#100
b00000000000000000101010101010101 #
0%
b00000000000000000000000000110010 (
1*
b00001 ,
b01010 -
b00100101 .
b001 /
b00000000000000000000000000110010 0
b00000000000000000101010101010101 1
b01010 2
13
#101
b00000000000000000000000000000000 #
1%
0*
b00000 ,
b00000 -
b00000000 .
b000 /
b00000000000000000000000000000000 0
b00000000000000000000000000000000 1
b00000 2
03
#102
b00000000000000000101010101010101 #
0%
b00000000000000000000000000110011 (
1*
b00001 ,
b01010 -
b00100101 .
b001 /
b00000000000000000000000000110011 0
b00000000000000000101010101010101 1
b01010 2
13
#103
b00000000000000000000000000000000 #
1%
0*
b00000 ,
b00000 -
b00000000 .
b000 /
b00000000000000000000000000000000 0
b00000000000000000000000000000000 1
b00000 2
03
#104
b00000000000000000101010101010101 #
0%
b00000000000000000000000000110100 (
1*
b00001 ,
b01010 -
b00100101 .
b001 /
b00000000000000000000000000110100 0
b00000000000000000101010101010101 1
b01010 2
13
#105
b00000000000000000000000000000000 #
1%
0*
b00000 ,
b00000 -
b00000000 .
b000 /
b00000000000000000000000000000000 0
b00000000000000000000000000000000 1
b00000 2
03
#106
b00000000000000000101010101010101 #
0%
b00000000000000000000000000110101 (
1*
b00001 ,
b01010 -
b00100101 .
b001 /
b00000000000000000000000000110101 0
b00000000000000000101010101010101 1
b01010 2
13
#107
b00000000000000000000000000000000 #
1%
0*
b00000 ,
b00000 -
b00000000 .
b000 /
b00000000000000000000000000000000 0
b00000000000000000000000000000000 1
b00000 2
03
#108
b00000000000000000101010101010101 #
0%
b00000000000000000000000000110110 (
1*
b00001 ,
b01010 -
b00100101 .
b001 /
b00000000000000000000000000110110 0
b00000000000000000101010101010101 1
b01010 2
13
#109
b00000000000000000000000000000000 #
1%
0*
b00000 ,
b00000 -
b00000000 .
b000 /
b00000000000000000000000000000000 0
b00000000000000000000000000000000 1
b00000 2
03
#110
b00000000000000000101010101010101 #
0%
b00000000000000000000000000110111 (
1*
b00001 ,
b01010 -
b00100101 .
b001 /
b00000000000000000000000000110111 0
b00000000000000000101010101010101 1
b01010 2
13
#111
b00000000000000000000000000000000 #
1%
0*
b00000 ,
b00000 -
b00000000 .
b000 /
b00000000000000000000000000000000 0
b00000000000000000000000000000000 1
b00000 2
03
#112
b00000000000000000101010101010101 #
0%
b00000000000000000000000000111000 (
1*
b00001 ,
b01010 -
b00100101 .
b001 /
b00000000000000000000000000111000 0
b00000000000000000101010101010101 1
b01010 2
13
#113
b00000000000000000000000000000000 #
1%
0*
b00000 ,
b00000 -
b00000000 .
b000 /
b00000000000000000000000000000000 0
b00000000000000000000000000000000 1
b00000 2
03
#114
b00000000000000000101010101010101 #
0%
b00000000000000000000000000111001 (
1*
b00001 ,
b01010 -
b00100101 .
b001 /
b00000000000000000000000000111001 0
b00000000000000000101010101010101 1
b01010 2
13
#115
b00000000000000000000000000000000 #
1%
0*
b00000 ,
b00000 -
b00000000 .
b000 /
b00000000000000000000000000000000 0
b00000000000000000000000000000000 1
b00000 2
03
#116
b00000000000000000101010101010101 #
0%
b00000000000000000000000000111010 (
1*
b00001 ,
b01010 -
b00100101 .
b001 /
b00000000000000000000000000111010 0
b00000000000000000101010101010101 1
b01010 2
13
#117
b00000000000000000000000000000000 #
1%
0*
b00000 ,
b00000 -
b00000000 .
b000 /
b00000000000000000000000000000000 0
b00000000000000000000000000000000 1
b00000 2
03
#118
b00000000000000000101010101010101 #
0%
b00000000000000000000000000111011 (
1*
b00001 ,
b01010 -
b00100101 .
b001 /
b00000000000000000000000000111011 0
b00000000000000000101010101010101 1
b01010 2
13
#119
b00000000000000000000000000000000 #
1%
0*
b00000 ,
b00000 -
b00000000 .
b000 /
b00000000000000000000000000000000 0
b00000000000000000000000000000000 1
b00000 2
03
#120
b00000000000000000101010101010101 #
0%
b00000000000000000000000000111100 (
1*
b00001 ,
b01010 -
b00100101 .
b001 /
b00000000000000000000000000111100 0
b00000000000000000101010101010101 1
b01010 2
13
#121
b00000000000000000000000000000000 #
1%
0*
b00000 ,
b00000 -
b00000000 .
b000 /
b00000000000000000000000000000000 0
b00000000000000000000000000000000 1
b00000 2
03
#122
b00000000000000000101010101010101 #
0%
b00000000000000000000000000111101 (
1*
b00001 ,
b01010 -
b00100101 .
b001 /
b00000000000000000000000000111101 0
b00000000000000000101010101010101 1
b01010 2
13
#123
b00000000000000000000000000000000 #
1%
0*
b00000 ,
b00000 -
b00000000 .
b000 /
b00000000000000000000000000000000 0
b00000000000000000000000000000000 1
b00000 2
03
#124
b00000000000000000101010101010101 #
0%
b00000000000000000000000000111110 (
1*
b00001 ,
b01010 -
b00100101 .
b001 /
b00000000000000000000000000111110 0
b00000000000000000101010101010101 1
b01010 2
13
#125
b00000000000000000000000000000000 #
1%
0*
b00000 ,
b00000 -
b00000000 .
b000 /
b00000000000000000000000000000000 0
b00000000000000000000000000000000 1
b00000 2
03
#126
b00000000000000000101010101010101 #
0%
b00000000000000000000000000111111 (
1*
b00001 ,
b01010 -
b00100101 .
b001 /
b00000000000000000000000000111111 0
b00000000000000000101010101010101 1
b01010 2
13
#127
b00000000000000000000000000000000 #
1%
0*
b00000 ,
b00000 -
b00000000 .
b000 /
b00000000000000000000000000000000 0
b00000000000000000000000000000000 1
b00000 2
03
#128
b00000000000000000101010101010101 #
0%
b00000000000000000000000001000000 (
1*
b00001 ,
b01010 -
b00100101 .
b001 /
b00000000000000000000000001000000 0
b00000000000000000101010101010101 1
b01010 2
13
