cpu/define.v
`define RstEnable 1'b1
`define RstDisable 1'b0
`define ZeroWord 32'h00000000
`define WriteEnable 1'b1
`define WriteDisable 1'b0
`define ReadEnable 1'b1
`define ReadDisable 1'b0
`define AluOpBus 7:0
`define AluSelBus 2:0
`define InstValid 1'b1
`define InstInvalid 1'b0
`define True_v 1'b1
`define False_v 1'b0
`define ChipEnable 1'b1
`define ChipDisable 1'b0

`define EXE_ORI 6'b001101
`define EXE_NOP 6'b000000

`define EXE_OR_OP 8'b00100101
`define EXE_NOP_OP 8'b00000000

`define EXE_RES_LOGIC 3'b001
`define EXE_RES_NOP 3'b000

`define InstAddrBus 31:0
`define InstBus 31:0
`define InstMemNum 131071 // 128KB
`define InstMemNumLog2 17

`define RegAddrBus 4:0
`define RegBus 31:0
`define RegWidth 32
`define DoubleRegWidth 64
`define DoubleRegBus 63:0
`define RegNum 32
`define RegNumLog2 5
`define NOPRegAddr 5'b0000

cpu/regfile.v
`include "define.v"
module regfile(
    input wire clk,
    input wire rst,

    input wire we,
    input wire[`RegAddrBus] waddr,
    input wire[`RegBus] wdata,

    input wire re1,
    input wire[`RegAddrBus] raddr1,
    output reg[`RegBus] rdata1,

    input wire re2,
    input wire[`RegAddrBus] raddr2,
    output reg[`RegBus] rdata2
);

    // the first reg is always zero
    reg[`RegBus] regs[0:`RegNum-1];

    always @ (posedge clk) begin
      if (rst == `RstEnable) begin
        if ((we == `WriteEnable) && (waddr != `RegNumLog2'h0)) begin
          regs[waddr] <= wdata;
        end
      end
    end

    always @ (*) begin
      if (rst == `RstEnable) begin
        rdata1 <= `ZeroWord;
      end else if (raddr1 == `RegNumLog2'h0) begin
        rdata1 <= `ZeroWord;
      end else if ((raddr1 == waddr) && (we == `WriteEnable)
                    && (re1 == `ReadEnable)) begin
        rdata1 <= wdata;
      end else if (re1 == `ReadEnable) begin
        rdata1 <= regs[raddr1];
      end else begin
        rdata1 <= regs[raddr1];
      end
    end

    always @ (*) begin
      if (rst == `RstEnable) begin
        rdata2 <= `ZeroWord;
      end else if (raddr2 == `RegNumLog2'h0) begin
        rdata2 <= `ZeroWord;
      end else if ((raddr2 == waddr) && (we == `WriteEnable)
                    && (re2 == `ReadEnable)) begin
        rdata2 <= wdata;
      end else if (re2 == `ReadEnable) begin
        rdata2 <= regs[raddr2];
      end else begin
        rdata2 <= regs[raddr2];
      end
    end

endmodule // regfile

cpu/id.v
`include "define.v"
module id(
    input wire rst,
    input wire[`InstAddrBus] pc_i,
    input wire[`InstBus] inst_i,

    input wire[`RegBus] reg1_data_i, // read reg1 data
    input wire[`RegBus] reg2_data_i, // read reg2 data

    output reg reg1_read_o, // read reg1 or not
    output reg reg2_read_o, // read reg2 or not
    output reg[`RegAddrBus] reg1_addr_o, // read reg1 num
    output reg[`RegAddrBus] reg2_addr_o, // read reg2 num

    output reg[`AluOpBus] aluop_o, // alu op
    output reg[`AluSelBus] alusel_o, // alu selector
    output reg[`RegBus] reg1_o, // reg1 passed to alu
    output reg[`RegBus] reg2_o, // reg2 passed to alu
    output reg[`RegAddrBus] wd_o, // output register num
    output reg wreg_o // output enabled
);
    wire[5:0] op = inst_i[31:26]; // op type
    wire[4:0] op2 = inst_i[10:6];
    wire[5:0] op3 = inst_i[5:0];
    wire[4:0] op4 = inst_i[20:16];

    reg[`RegBus] imm;
    reg instvalid;

    always @ (*) begin
      if (rst == `RstEnable) begin
        aluop_o <= `EXE_NOP_OP;
        alusel_o <= `EXE_RES_NOP;
        wd_o <= `NOPRegAddr;
        wreg_o <= `WriteDisable;
        instvalid <= `InstValid;
        reg1_read_o <= 1'0;
        reg2_read_o <= 1'0;
        reg1_addr_o <= `NOPRegAddr;
        reg2_addr_o <= `NOPRegAddr;
        imm <= `ZeroWord;
      end else begin
        aluop_o <= `EXE_NOP_OP;
        alusel_o <= `EXE_RES_NOP;
        wd_o <= inst_i[15:11];
        wreg_o <= `WriteDisable;
        instvalid <= `InstInvalid;
        reg1_read_o <= 1'0;
        reg2_read_o <= 1'0;
        reg1_addr_o <= inst_i[25:21];
        reg2_addr_o <= inst_i[20:16];
        imm <= `ZeroWord;

        case (op)
          `EXE_ORI: begin
            wreg_o <= `WriteEnable;
            aluop_o <= `EXE_OR_OP;
            alusel_o <= `EXE_RES_LOGIC;
            reg1_read_o <= 1'1; // read source from rs
            reg2_read_o <= 1'0; // use imm
            // unsigned extend
            imm <= {16'h0, inst_i[15:0]};
            wd_o <= inst_i[20:16];
            instvalid <= `InstValid;
          end
          default: begin
            
          end
        endcase
      end
    end

    always @ (*) begin
      if (rst == `RstEnable) begin
        reg1_o <= `ZeroWord;
      end else if (reg1_read_o == 1'b1) begin
        reg1_o <= reg1_data_i;
      end else if (reg1_read_o == 1'b0) begin
        reg1_o <= imm;
      end else begin
        reg1_o <= `ZeroWord;
      end
    end

    always @ (*) begin
      if (rst == `RstEnable) begin
        reg2_o <= `ZeroWord;
      end else if (reg2_read_o == 1'b1) begin
        reg2_o <= reg2_data_i;
      end else if (reg2_read_o == 1'b0) begin
        reg2_o <= imm;
      end else begin
        reg2_o <= `ZeroWord;
      end
    end

endmodule // id

cpu/if_id.v
`include "define.v"
module if_id(
    input wire clk,
    input wire rst,

    input wire[`InstAddrBus] if_pc,
    input wire[`InstBus] if_inst,

    output reg[`InstAddrBus] id_pc,
    output reg[`InstBus] id_inst
);

  always @ (posedge clk) begin
    if (rst == `RstEnable) begin
      id_pc <= `ZeroWord;
      id_inst <= `ZeroWord;
    end else begin
      id_pc <= if_pc;
      id_inst <= if_inst;
    end
  end

endmodule // if_id

cpu/rom.v
`include "define.v"
module rom(
  input wire ce,
  input wire[`InstAddrBus] addr,

  output reg[`InstBus] inst
);
    reg[`InstBus] rom[0:`InstMemNum-1];

    initial begin
        $readmemb ("rom.data", rom);
    end

    always @(*) begin
      if (ce == `ChipDisable) begin
        inst <= `ZeroWord;
      end else begin
        inst <= rom[addr[`InstMemNumLog2+1:2]];
      end
    end

endmodule // rom

cpu/pc_reg.v
`include "define.v"
module pc_reg (
    input wire clk,
    input wire rst,

    output reg[`InstAddrBus] pc,
    output reg ce
);

    always @ (posedge clk) begin
      if (rst == `RstEnable) begin
        ce <= `ChipDisable;
      end else begin
        ce <= `ChipEnable;
      end
    end

    always @ (posedge clk) begin
      if (ce == `ChipDisable) begin
        pc <= 32'h00000000;
      end else begin
        pc <= pc + 4'h4;
      end
    end

endmodule // pc_reg

cpu/if_and_id.v
`include "define.v"
module if_and_id(
    input wire clk,
    input wire rst
);

    wire[`InstAddrBus] pc;
    wire rom_ce;

    wire[`InstAddrBus] rom_data;
    wire[`InstAddrBus] id_pc_i;
    wire[`InstBus] id_inst_i;

    wire[`AluOpBus] id_aluop_o;
    wire[`AluSelBus] id_alusel_o;
    wire[`RegBus] id_reg1_o;
    wire[`RegBus] id_reg2_o;
    wire id_wreg_o;
    wire[`RegAddrBus] id_wd_o;

    wire wb_wreg_i;
    wire[`RegAddrBus] wb_wd_i;
    wire[`RegBus] wb_wdata_i;

    wire reg1_read; // read reg1 or not
    wire reg2_read;
    wire[`RegBus] reg1_data; // the data of reg1
    wire[`RegBus] reg2_data;
    wire[`RegAddrBus] reg1_addr; // the index or reg1
    wire[`RegAddrBus] reg2_addr;

    pc_reg pc_reg0(.clk(clk), .rst(rst),
                    .pc(pc), .ce(rom_ce));
    rom rom0(.ce(rom_ce), .addr(pc), .inst(rom_data));

    if_id if_id0(.clk(clk), .rst(rst), .if_pc(pc), .if_inst(rom_data),
                 .id_pc(id_pc_i), .id_inst(id_inst_i));

    id id0(.rst(rst), .pc_i(id_pc_i), .inst_i(id_inst_i),
            .reg1_data_i(reg1_data), .reg2_data_i(reg2_data),
            .reg1_read_o(reg1_read), .reg2_read_o(reg2_read),
            .reg1_addr_o(reg1_addr), .reg2_addr_o(reg2_addr),
            .aluop_o(id_aluop_o), .alusel_o(id_alusel_o),
            .reg1_o(id_reg1_o), .reg2_o(id_reg2_o),
            .wd_o(id_wd_o), .wreg_o(id_wreg_o));

    regfile regfile0(.clk(clk), .rst(rst),
                    .we(wb_wreg_i), .waddr(wb_wd_i),
                    .wdata(wb_wdata_i), .re1(reg1_read),
                    .raddr1(reg1_addr), .rdata1(reg1_data),
                    .re2(reg2_read), .raddr2(reg2_addr),
                    .rdata2(reg2_data));

endmodule // if_and_id

cpu/if_and_id.vcd
$version Generated by VerilatedVcd $end
$date Thu Jun 21 21:33:24 2018
 $end
$timescale   1ns $end

 $scope module TOP $end
  $var wire  1 V clk $end
  $var wire  1 W rst $end
  $scope module if_and_id $end
   $var wire  1 V clk $end
   $var wire  8 $ id_aluop_o [7:0] $end
   $var wire  3 % id_alusel_o [2:0] $end
   $var wire 32 1 id_inst_i [31:0] $end
   $var wire 32 0 id_pc_i [31:0] $end
   $var wire 32 X id_reg1_o [31:0] $end
   $var wire 32 Y id_reg2_o [31:0] $end
   $var wire  5 ' id_wd_o [4:0] $end
   $var wire  1 & id_wreg_o $end
   $var wire 32 . pc [31:0] $end
   $var wire  5 * reg1_addr [4:0] $end
   $var wire 32 Z reg1_data [31:0] $end
   $var wire  1 ( reg1_read $end
   $var wire  5 + reg2_addr [4:0] $end
   $var wire 32 [ reg2_data [31:0] $end
   $var wire  1 ) reg2_read $end
   $var wire  1 / rom_ce $end
   $var wire 32 # rom_data [31:0] $end
   $var wire  1 W rst $end
   $var wire  5 ] wb_wd_i [4:0] $end
   $var wire 32 ^ wb_wdata_i [31:0] $end
   $var wire  1 \ wb_wreg_i $end
   $scope module id0 $end
    $var wire  8 $ aluop_o [7:0] $end
    $var wire  3 % alusel_o [2:0] $end
    $var wire 32 , imm [31:0] $end
    $var wire 32 1 inst_i [31:0] $end
    $var wire  1 - instvalid $end
    $var wire  6 2 op [5:0] $end
    $var wire  5 3 op2 [4:0] $end
    $var wire  6 4 op3 [5:0] $end
    $var wire  5 5 op4 [4:0] $end
    $var wire 32 0 pc_i [31:0] $end
    $var wire  5 * reg1_addr_o [4:0] $end
    $var wire 32 Z reg1_data_i [31:0] $end
    $var wire 32 X reg1_o [31:0] $end
    $var wire  1 ( reg1_read_o $end
    $var wire  5 + reg2_addr_o [4:0] $end
    $var wire 32 [ reg2_data_i [31:0] $end
    $var wire 32 Y reg2_o [31:0] $end
    $var wire  1 ) reg2_read_o $end
    $var wire  1 W rst $end
    $var wire  5 ' wd_o [4:0] $end
    $var wire  1 & wreg_o $end
   $upscope $end
   $scope module if_id0 $end
    $var wire  1 V clk $end
    $var wire 32 1 id_inst [31:0] $end
    $var wire 32 0 id_pc [31:0] $end
    $var wire 32 # if_inst [31:0] $end
    $var wire 32 . if_pc [31:0] $end
    $var wire  1 W rst $end
   $upscope $end
   $scope module pc_reg0 $end
    $var wire  1 / ce $end
    $var wire  1 V clk $end
    $var wire 32 . pc [31:0] $end
    $var wire  1 W rst $end
   $upscope $end
   $scope module regfile0 $end
    $var wire  1 V clk $end
    $var wire  5 * raddr1 [4:0] $end
    $var wire  5 + raddr2 [4:0] $end
    $var wire 32 Z rdata1 [31:0] $end
    $var wire 32 [ rdata2 [31:0] $end
    $var wire  1 ( re1 $end
    $var wire  1 ) re2 $end
    $var wire 32 6 regs(0) [31:0] $end
    $var wire 32 7 regs(1) [31:0] $end
    $var wire 32 @ regs(10) [31:0] $end
    $var wire 32 A regs(11) [31:0] $end
    $var wire 32 B regs(12) [31:0] $end
    $var wire 32 C regs(13) [31:0] $end
    $var wire 32 D regs(14) [31:0] $end
    $var wire 32 E regs(15) [31:0] $end
    $var wire 32 F regs(16) [31:0] $end
    $var wire 32 G regs(17) [31:0] $end
    $var wire 32 H regs(18) [31:0] $end
    $var wire 32 I regs(19) [31:0] $end
    $var wire 32 8 regs(2) [31:0] $end
    $var wire 32 J regs(20) [31:0] $end
    $var wire 32 K regs(21) [31:0] $end
    $var wire 32 L regs(22) [31:0] $end
    $var wire 32 M regs(23) [31:0] $end
    $var wire 32 N regs(24) [31:0] $end
    $var wire 32 O regs(25) [31:0] $end
    $var wire 32 P regs(26) [31:0] $end
    $var wire 32 Q regs(27) [31:0] $end
    $var wire 32 R regs(28) [31:0] $end
    $var wire 32 S regs(29) [31:0] $end
    $var wire 32 9 regs(3) [31:0] $end
    $var wire 32 T regs(30) [31:0] $end
    $var wire 32 U regs(31) [31:0] $end
    $var wire 32 : regs(4) [31:0] $end
    $var wire 32 ; regs(5) [31:0] $end
    $var wire 32 < regs(6) [31:0] $end
    $var wire 32 = regs(7) [31:0] $end
    $var wire 32 > regs(8) [31:0] $end
    $var wire 32 ? regs(9) [31:0] $end
    $var wire  1 W rst $end
    $var wire  5 ] waddr [4:0] $end
    $var wire 32 ^ wdata [31:0] $end
    $var wire  1 \ we $end
   $upscope $end
   $scope module rom0 $end
    $var wire 32 . addr [31:0] $end
    $var wire  1 / ce $end
    $var wire 32 # inst [31:0] $end
   $upscope $end
  $upscope $end
 $upscope $end
$enddefinitions $end


#0
b00000000000000000000000000000000 #
b00000000 $
b000 %
0&
b00000 '
0(
0)
b00000 *
b00000 +
b00000000000000000000000000000000 ,
0-
b00000000000000000000000000000000 .
0/
b00000000000000000000000000000000 0
b00000000000000000000000000000000 1
b000000 2
b00000 3
b000000 4
b00000 5
b00000000000000000000000000000000 6
b00000000000000000000000000000000 7
b00000000000000000000000000000000 8
b00000000000000000000000000000000 9
b00000000000000000000000000000000 :
b00000000000000000000000000000000 ;
b00000000000000000000000000000000 <
b00000000000000000000000000000000 =
b00000000000000000000000000000000 >
b00000000000000000000000000000000 ?
b00000000000000000000000000000000 @
b00000000000000000000000000000000 A
b00000000000000000000000000000000 B
b00000000000000000000000000000000 C
b00000000000000000000000000000000 D
b00000000000000000000000000000000 E
b00000000000000000000000000000000 F
b00000000000000000000000000000000 G
b00000000000000000000000000000000 H
b00000000000000000000000000000000 I
b00000000000000000000000000000000 J
b00000000000000000000000000000000 K
b00000000000000000000000000000000 L
b00000000000000000000000000000000 M
b00000000000000000000000000000000 N
b00000000000000000000000000000000 O
b00000000000000000000000000000000 P
b00000000000000000000000000000000 Q
b00000000000000000000000000000000 R
b00000000000000000000000000000000 S
b00000000000000000000000000000000 T
b00000000000000000000000000000000 U
0V
0W
b00000000000000000000000000000000 X
b00000000000000000000000000000000 Y
b00000000000000000000000000000000 Z
b00000000000000000000000000000000 [
0\
b00000 ]
b00000000000000000000000000000000 ^
#1
b00110100001010100101010101010101 #
1/
1V
#2
0V
#3
b00110100010001100001001000110100 #
b00100101 $
b001 %
1&
b01010 '
1(
b00001 *
b01010 +
b00000000000000000101010101010101 ,
1-
b00000000000000000000000000000100 .
b00110100001010100101010101010101 1
b001101 2
b10101 3
b010101 4
b01010 5
1V
b00000000000000000101010101010101 Y
#4
0V
#5
b00110100001010100101010101010101 #
b00110 '
b00010 *
b00110 +
b00000000000000000001001000110100 ,
b00000000000000000000000000001000 .
b00000000000000000000000000000100 0
b00110100010001100001001000110100 1
b01000 3
b110100 4
b00110 5
1V
b00000000000000000001001000110100 Y
#6
0V
#7
b00110100010001100001001000110100 #
b01010 '
b00001 *
b01010 +
b00000000000000000101010101010101 ,
b00000000000000000000000000001100 .
b00000000000000000000000000001000 0
b00110100001010100101010101010101 1
b10101 3
b010101 4
b01010 5
1V
b00000000000000000101010101010101 Y
#8
0V
#9
b00110100001010100101010101010101 #
b00110 '
b00010 *
b00110 +
b00000000000000000001001000110100 ,
b00000000000000000000000000010000 .
b00000000000000000000000000001100 0
b00110100010001100001001000110100 1
b01000 3
b110100 4
b00110 5
1V
b00000000000000000001001000110100 Y
#10
0V
#11
b00110100010001100001001000110100 #
b01010 '
b00001 *
b01010 +
b00000000000000000101010101010101 ,
b00000000000000000000000000010100 .
b00000000000000000000000000010000 0
b00110100001010100101010101010101 1
b10101 3
b010101 4
b01010 5
1V
b00000000000000000101010101010101 Y
#12
0V
#13
b00110100001010100101010101010101 #
b00110 '
b00010 *
b00110 +
b00000000000000000001001000110100 ,
b00000000000000000000000000011000 .
b00000000000000000000000000010100 0
b00110100010001100001001000110100 1
b01000 3
b110100 4
b00110 5
1V
b00000000000000000001001000110100 Y
#14
0V
#15
b00110100010001100001001000110100 #
b01010 '
b00001 *
b01010 +
b00000000000000000101010101010101 ,
b00000000000000000000000000011100 .
b00000000000000000000000000011000 0
b00110100001010100101010101010101 1
b10101 3
b010101 4
b01010 5
1V
b00000000000000000101010101010101 Y
#16
0V
#17
b00110100001010100101010101010101 #
b00110 '
b00010 *
b00110 +
b00000000000000000001001000110100 ,
b00000000000000000000000000100000 .
b00000000000000000000000000011100 0
b00110100010001100001001000110100 1
b01000 3
b110100 4
b00110 5
1V
b00000000000000000001001000110100 Y
#18
0V
#19
b00110100010001100001001000110100 #
b01010 '
b00001 *
b01010 +
b00000000000000000101010101010101 ,
b00000000000000000000000000100100 .
b00000000000000000000000000100000 0
b00110100001010100101010101010101 1
b10101 3
b010101 4
b01010 5
1V
b00000000000000000101010101010101 Y
#20
0V
#21
b00110100001010100101010101010101 #
b00110 '
b00010 *
b00110 +
b00000000000000000001001000110100 ,
b00000000000000000000000000101000 .
b00000000000000000000000000100100 0
b00110100010001100001001000110100 1
b01000 3
b110100 4
b00110 5
1V
b00000000000000000001001000110100 Y
#22
0V
#23
b00110100010001100001001000110100 #
b01010 '
b00001 *
b01010 +
b00000000000000000101010101010101 ,
b00000000000000000000000000101100 .
b00000000000000000000000000101000 0
b00110100001010100101010101010101 1
b10101 3
b010101 4
b01010 5
1V
b00000000000000000101010101010101 Y
#24
0V
#25
b00110100001010100101010101010101 #
b00110 '
b00010 *
b00110 +
b00000000000000000001001000110100 ,
b00000000000000000000000000110000 .
b00000000000000000000000000101100 0
b00110100010001100001001000110100 1
b01000 3
b110100 4
b00110 5
1V
b00000000000000000001001000110100 Y
#26
0V
#27
b00110100010001100001001000110100 #
b01010 '
b00001 *
b01010 +
b00000000000000000101010101010101 ,
b00000000000000000000000000110100 .
b00000000000000000000000000110000 0
b00110100001010100101010101010101 1
b10101 3
b010101 4
b01010 5
1V
b00000000000000000101010101010101 Y
#28
0V
#29
b00110100001010100101010101010101 #
b00110 '
b00010 *
b00110 +
b00000000000000000001001000110100 ,
b00000000000000000000000000111000 .
b00000000000000000000000000110100 0
b00110100010001100001001000110100 1
b01000 3
b110100 4
b00110 5
1V
b00000000000000000001001000110100 Y
#30
0V
#31
b00110100010001100001001000110100 #
b01010 '
b00001 *
b01010 +
b00000000000000000101010101010101 ,
b00000000000000000000000000111100 .
b00000000000000000000000000111000 0
b00110100001010100101010101010101 1
b10101 3
b010101 4
b01010 5
1V
b00000000000000000101010101010101 Y
#32
0V
#33
b00110100001010100101010101010101 #
b00110 '
b00010 *
b00110 +
b00000000000000000001001000110100 ,
b00000000000000000000000001000000 .
b00000000000000000000000000111100 0
b00110100010001100001001000110100 1
b01000 3
b110100 4
b00110 5
1V
b00000000000000000001001000110100 Y
#34
0V
#35
b00110100010001100001001000110100 #
b01010 '
b00001 *
b01010 +
b00000000000000000101010101010101 ,
b00000000000000000000000001000100 .
b00000000000000000000000001000000 0
b00110100001010100101010101010101 1
b10101 3
b010101 4
b01010 5
1V
b00000000000000000101010101010101 Y
#36
0V
#37
b00110100001010100101010101010101 #
b00110 '
b00010 *
b00110 +
b00000000000000000001001000110100 ,
b00000000000000000000000001001000 .
b00000000000000000000000001000100 0
b00110100010001100001001000110100 1
b01000 3
b110100 4
b00110 5
1V
b00000000000000000001001000110100 Y
#38
0V
#39
b00110100010001100001001000110100 #
b01010 '
b00001 *
b01010 +
b00000000000000000101010101010101 ,
b00000000000000000000000001001100 .
b00000000000000000000000001001000 0
b00110100001010100101010101010101 1
b10101 3
b010101 4
b01010 5
1V
b00000000000000000101010101010101 Y
#40
0V
#41
b00110100001010100101010101010101 #
b00110 '
b00010 *
b00110 +
b00000000000000000001001000110100 ,
b00000000000000000000000001010000 .
b00000000000000000000000001001100 0
b00110100010001100001001000110100 1
b01000 3
b110100 4
b00110 5
1V
b00000000000000000001001000110100 Y
#42
0V
#43
b00110100010001100001001000110100 #
b01010 '
b00001 *
b01010 +
b00000000000000000101010101010101 ,
b00000000000000000000000001010100 .
b00000000000000000000000001010000 0
b00110100001010100101010101010101 1
b10101 3
b010101 4
b01010 5
1V
b00000000000000000101010101010101 Y
#44
0V
#45
b00110100001010100101010101010101 #
b00110 '
b00010 *
b00110 +
b00000000000000000001001000110100 ,
b00000000000000000000000001011000 .
b00000000000000000000000001010100 0
b00110100010001100001001000110100 1
b01000 3
b110100 4
b00110 5
1V
b00000000000000000001001000110100 Y
#46
0V
#47
b00110100010001100001001000110100 #
b01010 '
b00001 *
b01010 +
b00000000000000000101010101010101 ,
b00000000000000000000000001011100 .
b00000000000000000000000001011000 0
b00110100001010100101010101010101 1
b10101 3
b010101 4
b01010 5
1V
b00000000000000000101010101010101 Y
#48
0V
#49
b00110100001010100101010101010101 #
b00110 '
b00010 *
b00110 +
b00000000000000000001001000110100 ,
b00000000000000000000000001100000 .
b00000000000000000000000001011100 0
b00110100010001100001001000110100 1
b01000 3
b110100 4
b00110 5
1V
b00000000000000000001001000110100 Y
#50
0V
#51
b00110100010001100001001000110100 #
b01010 '
b00001 *
b01010 +
b00000000000000000101010101010101 ,
b00000000000000000000000001100100 .
b00000000000000000000000001100000 0
b00110100001010100101010101010101 1
b10101 3
b010101 4
b01010 5
1V
b00000000000000000101010101010101 Y
#52
0V
#53
b00110100001010100101010101010101 #
b00110 '
b00010 *
b00110 +
b00000000000000000001001000110100 ,
b00000000000000000000000001101000 .
b00000000000000000000000001100100 0
b00110100010001100001001000110100 1
b01000 3
b110100 4
b00110 5
1V
b00000000000000000001001000110100 Y
#54
0V
#55
b00110100010001100001001000110100 #
b01010 '
b00001 *
b01010 +
b00000000000000000101010101010101 ,
b00000000000000000000000001101100 .
b00000000000000000000000001101000 0
b00110100001010100101010101010101 1
b10101 3
b010101 4
b01010 5
1V
b00000000000000000101010101010101 Y
#56
0V
#57
b00110100001010100101010101010101 #
b00110 '
b00010 *
b00110 +
b00000000000000000001001000110100 ,
b00000000000000000000000001110000 .
b00000000000000000000000001101100 0
b00110100010001100001001000110100 1
b01000 3
b110100 4
b00110 5
1V
b00000000000000000001001000110100 Y
#58
0V
#59
b00110100010001100001001000110100 #
b01010 '
b00001 *
b01010 +
b00000000000000000101010101010101 ,
b00000000000000000000000001110100 .
b00000000000000000000000001110000 0
b00110100001010100101010101010101 1
b10101 3
b010101 4
b01010 5
1V
b00000000000000000101010101010101 Y
#60
0V
#61
b00110100001010100101010101010101 #
b00110 '
b00010 *
b00110 +
b00000000000000000001001000110100 ,
b00000000000000000000000001111000 .
b00000000000000000000000001110100 0
b00110100010001100001001000110100 1
b01000 3
b110100 4
b00110 5
1V
b00000000000000000001001000110100 Y
#62
0V
#63
b00110100010001100001001000110100 #
b01010 '
b00001 *
b01010 +
b00000000000000000101010101010101 ,
b00000000000000000000000001111100 .
b00000000000000000000000001111000 0
b00110100001010100101010101010101 1
b10101 3
b010101 4
b01010 5
1V
b00000000000000000101010101010101 Y
#64
0V
#65
b00110100001010100101010101010101 #
b00110 '
b00010 *
b00110 +
b00000000000000000001001000110100 ,
b00000000000000000000000010000000 .
b00000000000000000000000001111100 0
b00110100010001100001001000110100 1
b01000 3
b110100 4
b00110 5
1V
b00000000000000000001001000110100 Y
#66
0V
#67
b00110100010001100001001000110100 #
b01010 '
b00001 *
b01010 +
b00000000000000000101010101010101 ,
b00000000000000000000000010000100 .
b00000000000000000000000010000000 0
b00110100001010100101010101010101 1
b10101 3
b010101 4
b01010 5
1V
b00000000000000000101010101010101 Y
#68
0V
#69
b00110100001010100101010101010101 #
b00110 '
b00010 *
b00110 +
b00000000000000000001001000110100 ,
b00000000000000000000000010001000 .
b00000000000000000000000010000100 0
b00110100010001100001001000110100 1
b01000 3
b110100 4
b00110 5
1V
b00000000000000000001001000110100 Y
#70
0V
#71
b00110100010001100001001000110100 #
b01010 '
b00001 *
b01010 +
b00000000000000000101010101010101 ,
b00000000000000000000000010001100 .
b00000000000000000000000010001000 0
b00110100001010100101010101010101 1
b10101 3
b010101 4
b01010 5
1V
b00000000000000000101010101010101 Y
#72
0V
#73
b00110100001010100101010101010101 #
b00110 '
b00010 *
b00110 +
b00000000000000000001001000110100 ,
b00000000000000000000000010010000 .
b00000000000000000000000010001100 0
b00110100010001100001001000110100 1
b01000 3
b110100 4
b00110 5
1V
b00000000000000000001001000110100 Y
#74
0V
#75
b00110100010001100001001000110100 #
b01010 '
b00001 *
b01010 +
b00000000000000000101010101010101 ,
b00000000000000000000000010010100 .
b00000000000000000000000010010000 0
b00110100001010100101010101010101 1
b10101 3
b010101 4
b01010 5
1V
b00000000000000000101010101010101 Y
#76
0V
#77
b00110100001010100101010101010101 #
b00110 '
b00010 *
b00110 +
b00000000000000000001001000110100 ,
b00000000000000000000000010011000 .
b00000000000000000000000010010100 0
b00110100010001100001001000110100 1
b01000 3
b110100 4
b00110 5
1V
b00000000000000000001001000110100 Y
#78
0V
#79
b00110100010001100001001000110100 #
b01010 '
b00001 *
b01010 +
b00000000000000000101010101010101 ,
b00000000000000000000000010011100 .
b00000000000000000000000010011000 0
b00110100001010100101010101010101 1
b10101 3
b010101 4
b01010 5
1V
b00000000000000000101010101010101 Y
#80
0V
#81
b00110100001010100101010101010101 #
b00110 '
b00010 *
b00110 +
b00000000000000000001001000110100 ,
b00000000000000000000000010100000 .
b00000000000000000000000010011100 0
b00110100010001100001001000110100 1
b01000 3
b110100 4
b00110 5
1V
b00000000000000000001001000110100 Y
#82
0V
#83
b00110100010001100001001000110100 #
b01010 '
b00001 *
b01010 +
b00000000000000000101010101010101 ,
b00000000000000000000000010100100 .
b00000000000000000000000010100000 0
b00110100001010100101010101010101 1
b10101 3
b010101 4
b01010 5
1V
b00000000000000000101010101010101 Y
#84
0V
#85
b00110100001010100101010101010101 #
b00110 '
b00010 *
b00110 +
b00000000000000000001001000110100 ,
b00000000000000000000000010101000 .
b00000000000000000000000010100100 0
b00110100010001100001001000110100 1
b01000 3
b110100 4
b00110 5
1V
b00000000000000000001001000110100 Y
#86
0V
#87
b00110100010001100001001000110100 #
b01010 '
b00001 *
b01010 +
b00000000000000000101010101010101 ,
b00000000000000000000000010101100 .
b00000000000000000000000010101000 0
b00110100001010100101010101010101 1
b10101 3
b010101 4
b01010 5
1V
b00000000000000000101010101010101 Y
#88
0V
#89
b00110100001010100101010101010101 #
b00110 '
b00010 *
b00110 +
b00000000000000000001001000110100 ,
b00000000000000000000000010110000 .
b00000000000000000000000010101100 0
b00110100010001100001001000110100 1
b01000 3
b110100 4
b00110 5
1V
b00000000000000000001001000110100 Y
#90
0V
#91
b00110100010001100001001000110100 #
b01010 '
b00001 *
b01010 +
b00000000000000000101010101010101 ,
b00000000000000000000000010110100 .
b00000000000000000000000010110000 0
b00110100001010100101010101010101 1
b10101 3
b010101 4
b01010 5
1V
b00000000000000000101010101010101 Y
#92
0V
#93
b00110100001010100101010101010101 #
b00110 '
b00010 *
b00110 +
b00000000000000000001001000110100 ,
b00000000000000000000000010111000 .
b00000000000000000000000010110100 0
b00110100010001100001001000110100 1
b01000 3
b110100 4
b00110 5
1V
b00000000000000000001001000110100 Y
#94
0V
#95
b00110100010001100001001000110100 #
b01010 '
b00001 *
b01010 +
b00000000000000000101010101010101 ,
b00000000000000000000000010111100 .
b00000000000000000000000010111000 0
b00110100001010100101010101010101 1
b10101 3
b010101 4
b01010 5
1V
b00000000000000000101010101010101 Y
#96
0V
#97
b00110100001010100101010101010101 #
b00110 '
b00010 *
b00110 +
b00000000000000000001001000110100 ,
b00000000000000000000000011000000 .
b00000000000000000000000010111100 0
b00110100010001100001001000110100 1
b01000 3
b110100 4
b00110 5
1V
b00000000000000000001001000110100 Y
#98
0V
#99
b00110100010001100001001000110100 #
b01010 '
b00001 *
b01010 +
b00000000000000000101010101010101 ,
b00000000000000000000000011000100 .
b00000000000000000000000011000000 0
b00110100001010100101010101010101 1
b10101 3
b010101 4
b01010 5
1V
b00000000000000000101010101010101 Y
#100
0V
#101
b00110100001010100101010101010101 #
b00110 '
b00010 *
b00110 +
b00000000000000000001001000110100 ,
b00000000000000000000000011001000 .
b00000000000000000000000011000100 0
b00110100010001100001001000110100 1
b01000 3
b110100 4
b00110 5
1V
b00000000000000000001001000110100 Y
#102
0V
#103
b00110100010001100001001000110100 #
b01010 '
b00001 *
b01010 +
b00000000000000000101010101010101 ,
b00000000000000000000000011001100 .
b00000000000000000000000011001000 0
b00110100001010100101010101010101 1
b10101 3
b010101 4
b01010 5
1V
b00000000000000000101010101010101 Y
#104
0V
#105
b00110100001010100101010101010101 #
b00110 '
b00010 *
b00110 +
b00000000000000000001001000110100 ,
b00000000000000000000000011010000 .
b00000000000000000000000011001100 0
b00110100010001100001001000110100 1
b01000 3
b110100 4
b00110 5
1V
b00000000000000000001001000110100 Y
#106
0V
#107
b00110100010001100001001000110100 #
b01010 '
b00001 *
b01010 +
b00000000000000000101010101010101 ,
b00000000000000000000000011010100 .
b00000000000000000000000011010000 0
b00110100001010100101010101010101 1
b10101 3
b010101 4
b01010 5
1V
b00000000000000000101010101010101 Y
#108
0V
#109
b00110100001010100101010101010101 #
b00110 '
b00010 *
b00110 +
b00000000000000000001001000110100 ,
b00000000000000000000000011011000 .
b00000000000000000000000011010100 0
b00110100010001100001001000110100 1
b01000 3
b110100 4
b00110 5
1V
b00000000000000000001001000110100 Y
#110
0V
#111
b00110100010001100001001000110100 #
b01010 '
b00001 *
b01010 +
b00000000000000000101010101010101 ,
b00000000000000000000000011011100 .
b00000000000000000000000011011000 0
b00110100001010100101010101010101 1
b10101 3
b010101 4
b01010 5
1V
b00000000000000000101010101010101 Y
#112
0V
